{
  "level": 16,
  "name": "빙결 지대",
  "chapter": 2,
  "solvable": true,
  "min_ink": 162,
  "effort": 12,
  "rollouts": 376,
  "elapsed_ms": 258886,
  "budget": {
    "chalk": 326,
    "heat": 0,
    "frost": 0
  },
  "solutions": [
    {
      "ink": 162,
      "ticks": 1014,
      "strokes": [
        {
          "ink": "chalk",
          "x0": 91,
          "y0": 68,
          "x1": 15,
          "y1": 62
        }
      ],
      "gravity_taps": []
    },
    {
      "ink": 164,
      "ticks": 770,
      "strokes": [
        {
          "ink": "chalk",
          "x0": 92,
          "y0": 68,
          "x1": 15,
          "y1": 62
        }
      ],
      "gravity_taps": []
    },
    {
      "ink": 164,
      "ticks": 652,
      "strokes": [
        {
          "ink": "chalk",
          "x0": 91,
          "y0": 70,
          "x1": 15,
          "y1": 62
        }
      ],
      "gravity_taps": []
    },
    {
      "ink": 164,
      "ticks": 630,
      "strokes": [
        {
          "ink": "chalk",
          "x0": 91,
          "y0": 68,
          "x1": 15,
          "y1": 60
        }
      ],
      "gravity_taps": []
    },
    {
      "ink": 164,
      "ticks": 852,
      "strokes": [
        {
          "ink": "chalk",
          "x0": 91,
          "y0": 68,
          "x1": 14,
          "y1": 62
        }
      ],
      "gravity_taps": []
    }
  ],
  "probes": {}
}