{
  "level": 47,
  "name": "재의 방패",
  "chapter": 3,
  "solvable": true,
  "min_ink": 0,
  "effort": 1,
  "rollouts": 15,
  "elapsed_ms": 4997,
  "budget": {
    "chalk": 58,
    "heat": 17,
    "frost": 0
  },
  "solutions": [
    {
      "ink": 0,
      "ticks": 288,
      "strokes": [],
      "gravity_taps": []
    },
    {
      "ink": 0,
      "ticks": 288,
      "strokes": [
        {
          "ink": "chalk",
          "x0": 104,
          "y0": 276,
          "x1": 96,
          "y1": 292
        }
      ],
      "gravity_taps": []
    },
    {
      "ink": 0,
      "ticks": 288,
      "strokes": [
        {
          "ink": "chalk",
          "x0": 36,
          "y0": 152,
          "x1": 72,
          "y1": 316
        }
      ],
      "gravity_taps": []
    },
    {
      "ink": 0,
      "ticks": 288,
      "strokes": [
        {
          "ink": "heat",
          "x0": 72,
          "y0": 88,
          "x1": 76,
          "y1": 300
        },
        {
          "ink": "heat",
          "x0": 16,
          "y0": 96,
          "x1": 76,
          "y1": 308
        }
      ],
      "gravity_taps": []
    },
    {
      "ink": 12,
      "ticks": 288,
      "strokes": [
        {
          "ink": "chalk",
          "x0": 128,
          "y0": 292,
          "x1": 24,
          "y1": 276
        },
        {
          "ink": "chalk",
          "x0": 8,
          "y0": 116,
          "x1": 60,
          "y1": 292
        },
        {
          "ink": "chalk",
          "x0": 122,
          "y0": 208,
          "x1": 122,
          "y1": 212
        }
      ],
      "gravity_taps": []
    }
  ],
  "probes": {
    "no_ink_chalk": {
      "solvable": true,
      "min_ink": 0
    },
    "no_ink_heat": {
      "solvable": true,
      "min_ink": 0
    }
  }
}